[
  {
    "id": 146691,
    "website_id": 18861,
    "status": 4,
    "created_at": "2016-12-02T15:30:02.000Z",
    "updated_at": "2016-12-02T16:01:14.000Z",
    "language_id": 1,
    "title": "Winter Manfrotto Contest",
    "permlink": "http://www.manfrottoimaginemore.com/2016/11/15/winter-manfrotto-contest/",
    "tas_url": null,
    "tas_port": null,
    "list_type": null,
    "list_id": null,
    "last_operation": null,
    "pending_tas": 0,
    "error_description": null,
    "delivered": null,
    "note": "",
    "idkey": null,
    "cms_id": "post_67961_en_zh-hant",
    "container": null,
    "notified": 1,
    "tp_id": 95002,
    "word_count": 131
  },
  {
    "id": 147873,
    "website_id": 69873,
    "status": 4,
    "created_at": "2017-01-23T21:35:15.000Z",
    "updated_at": "2017-01-23T22:00:37.000Z",
    "language_id": 1,
    "title": "1.6mm CleanStixx® Optical Grade Cleaning Stick",
    "permlink": "https://sticklers.microcare.com/products/product/1-6mm-cleanstixx-optical-grade-cleaning-stick/",
    "tas_url": null,
    "tas_port": null,
    "list_type": null,
    "list_id": null,
    "last_operation": null,
    "pending_tas": 0,
    "error_description": null,
    "delivered": null,
    "note": "",
    "idkey": null,
    "cms_id": "product_239_en_zh-hant",
    "container": null,
    "notified": 1,
    "tp_id": 103077,
    "word_count": 195
  },
  {
    "id": 147881,
    "website_id": 69873,
    "status": 4,
    "created_at": "2017-01-23T21:35:21.000Z",
    "updated_at": "2017-01-23T22:00:37.000Z",
    "language_id": 1,
    "title": "1.25mm CleanStixx® Optical Grade Cleaning Stick",
    "permlink": "https://sticklers.microcare.com/products/product/1-25mm-cleanstixx-optical-grade-cleaning-stick/",
    "tas_url": null,
    "tas_port": null,
    "list_type": null,
    "list_id": null,
    "last_operation": null,
    "pending_tas": 0,
    "error_description": null,
    "delivered": null,
    "note": "",
    "idkey": null,
    "cms_id": "product_5865_en_zh-hant",
    "container": null,
    "notified": 1,
    "tp_id": 103085,
    "word_count": 189
  },
  {
    "id": 147885,
    "website_id": 69873,
    "status": 4,
    "created_at": "2017-01-23T21:35:27.000Z",
    "updated_at": "2017-01-23T22:00:37.000Z",
    "language_id": 1,
    "title": "Pin Termini CleanStixx® Optical Grade Cleaning Stick",
    "permlink": "https://sticklers.microcare.com/products/product/pin-termini-cleanstixx-optical-grade-cleaning-stick/",
    "tas_url": null,
    "tas_port": null,
    "list_type": null,
    "list_id": null,
    "last_operation": null,
    "pending_tas": 0,
    "error_description": null,
    "delivered": null,
    "note": "",
    "idkey": null,
    "cms_id": "product_5866_en_zh-hant",
    "container": null,
    "notified": 1,
    "tp_id": 103089,
    "word_count": 197
  },
  {
    "id": 147889,
    "website_id": 69873,
    "status": 4,
    "created_at": "2017-01-23T21:35:28.000Z",
    "updated_at": "2017-01-23T22:00:37.000Z",
    "language_id": 1,
    "title": "2.5mm CleanStixx® Optical Grade Cleaning Stick",
    "permlink": "https://sticklers.microcare.com/products/product/2-5mm-cleanstixx-optical-grade-cleaning-stick/",
    "tas_url": null,
    "tas_port": null,
    "list_type": null,
    "list_id": null,
    "last_operation": null,
    "pending_tas": 0,
    "error_description": null,
    "delivered": null,
    "note": "",
    "idkey": null,
    "cms_id": "product_5875_en_zh-hant",
    "container": null,
    "notified": 1,
    "tp_id": 103093,
    "word_count": 234
  },
  {
    "id": 147893,
    "website_id": 69873,
    "status": 4,
    "created_at": "2017-01-23T21:35:29.000Z",
    "updated_at": "2017-01-23T22:00:37.000Z",
    "language_id": 1,
    "title": "MT CleanStixx® Optical Grade Cleaning Stick",
    "permlink": "https://sticklers.microcare.com/products/product/mt-cleanstixx-optical-grade-cleaning-stick/",
    "tas_url": null,
    "tas_port": null,
    "list_type": null,
    "list_id": null,
    "last_operation": null,
    "pending_tas": 0,
    "error_description": null,
    "delivered": null,
    "note": "",
    "idkey": null,
    "cms_id": "product_5877_en_zh-hant",
    "container": null,
    "notified": 1,
    "tp_id": 103097,
    "word_count": 151
  },
  {
    "id": 147897,
    "website_id": 69873,
    "status": 4,
    "created_at": "2017-01-23T21:35:30.000Z",
    "updated_at": "2017-01-23T22:00:37.000Z",
    "language_id": 1,
    "title": "CleanWipes® 400 Portable Cleaning Box",
    "permlink": "https://sticklers.microcare.com/products/product/cleanwipes-400-portable-cleaning-box/",
    "tas_url": null,
    "tas_port": null,
    "list_type": null,
    "list_id": null,
    "last_operation": null,
    "pending_tas": 0,
    "error_description": null,
    "delivered": null,
    "note": "",
    "idkey": null,
    "cms_id": "product_5880_en_zh-hant",
    "container": null,
    "notified": 1,
    "tp_id": 103101,
    "word_count": 127
  },
  {
    "id": 147901,
    "website_id": 69873,
    "status": 4,
    "created_at": "2017-01-23T21:35:30.000Z",
    "updated_at": "2017-01-23T22:00:37.000Z",
    "language_id": 1,
    "title": "CleanWipes® 3200 Jumbo Connector Cleaning Box",
    "permlink": "https://sticklers.microcare.com/products/product/cleanwipes-3200-jumbo-connector-cleaning-box/",
    "tas_url": null,
    "tas_port": null,
    "list_type": null,
    "list_id": null,
    "last_operation": null,
    "pending_tas": 0,
    "error_description": null,
    "delivered": null,
    "note": "",
    "idkey": null,
    "cms_id": "product_5883_en_zh-hant",
    "container": null,
    "notified": 1,
    "tp_id": 103105,
    "word_count": 129
  },
  {
    "id": 147905,
    "website_id": 69873,
    "status": 4,
    "created_at": "2017-01-23T21:35:31.000Z",
    "updated_at": "2017-01-23T22:00:37.000Z",
    "language_id": 1,
    "title": "Sticklers® Fiber Optic Cleaning Kit",
    "permlink": "https://sticklers.microcare.com/products/product/sticklers-fiber-optic-cleaning-kit/",
    "tas_url": null,
    "tas_port": null,
    "list_type": null,
    "list_id": null,
    "last_operation": null,
    "pending_tas": 0,
    "error_description": null,
    "delivered": null,
    "note": "",
    "idkey": null,
    "cms_id": "product_5885_en_zh-hant",
    "container": null,
    "notified": 1,
    "tp_id": 103109,
    "word_count": 168
  },
  {
    "id": 147909,
    "website_id": 69873,
    "status": 4,
    "created_at": "2017-01-23T21:35:32.000Z",
    "updated_at": "2017-01-23T22:00:37.000Z",
    "language_id": 1,
    "title": "2.5mm CleanClicker® 750 Click-to-Clean Tool",
    "permlink": "https://sticklers.microcare.com/products/product/2-5mm-cleanclicker-750-click-to-clean-tool/",
    "tas_url": null,
    "tas_port": null,
    "list_type": null,
    "list_id": null,
    "last_operation": null,
    "pending_tas": 0,
    "error_description": null,
    "delivered": null,
    "note": "",
    "idkey": null,
    "cms_id": "product_5891_en_zh-hant",
    "container": null,
    "notified": 1,
    "tp_id": 103113,
    "word_count": 216
  },
  {
    "id": 147913,
    "website_id": 69873,
    "status": 4,
    "created_at": "2017-01-23T21:35:33.000Z",
    "updated_at": "2017-01-23T22:00:37.000Z",
    "language_id": 1,
    "title": "CleanClicker® Keyless MPO Click-to-Clean Tool",
    "permlink": "https://sticklers.microcare.com/products/product/cleanclicker-keyless-mpo-click-to-clean-tool/",
    "tas_url": null,
    "tas_port": null,
    "list_type": null,
    "list_id": null,
    "last_operation": null,
    "pending_tas": 0,
    "error_description": null,
    "delivered": null,
    "note": "",
    "idkey": null,
    "cms_id": "product_5895_en_zh-hant",
    "container": null,
    "notified": 1,
    "tp_id": 103117,
    "word_count": 166
  },
  {
    "id": 147917,
    "website_id": 69873,
    "status": 4,
    "created_at": "2017-01-23T21:35:34.000Z",
    "updated_at": "2017-01-23T22:00:37.000Z",
    "language_id": 1,
    "title": "CleanBlast® HFE-Based Cleaning Fluid (Single bottle)",
    "permlink": "https://sticklers.microcare.com/products/product/cleanblast-hfe-based-cleaning-fluid-single-bottle/",
    "tas_url": null,
    "tas_port": null,
    "list_type": null,
    "list_id": null,
    "last_operation": null,
    "pending_tas": 0,
    "error_description": null,
    "delivered": null,
    "note": "",
    "idkey": null,
    "cms_id": "product_6747_en_zh-hant",
    "container": null,
    "notified": 1,
    "tp_id": 103121,
    "word_count": 397
  },
  {
    "id": 147920,
    "website_id": 69873,
    "status": 4,
    "created_at": "2017-01-23T21:35:34.000Z",
    "updated_at": "2017-01-23T22:00:37.000Z",
    "language_id": 1,
    "title": "CleanBlast® HFE-Based Cleaning Fluid (Six Bottles in a Case)",
    "permlink": "https://sticklers.microcare.com/products/product/cleanblast-hfe-based-cleaning-fluid-six-bottles-case/",
    "tas_url": null,
    "tas_port": null,
    "list_type": null,
    "list_id": null,
    "last_operation": null,
    "pending_tas": 0,
    "error_description": null,
    "delivered": null,
    "note": "",
    "idkey": null,
    "cms_id": "product_6860_en_zh-hant",
    "container": null,
    "notified": 1,
    "tp_id": 103124,
    "word_count": 43
  },
  {
    "id": 147928,
    "website_id": 69873,
    "status": 4,
    "created_at": "2017-01-23T21:35:36.000Z",
    "updated_at": "2017-01-23T22:00:37.000Z",
    "language_id": 1,
    "title": "Sticklers® High-Volume Fiber Optic Cleaning Kit",
    "permlink": "https://sticklers.microcare.com/products/product/sticklers-high-volume-fiber-optic-cleaning-kit/",
    "tas_url": null,
    "tas_port": null,
    "list_type": null,
    "list_id": null,
    "last_operation": null,
    "pending_tas": 0,
    "error_description": null,
    "delivered": null,
    "note": "",
    "idkey": null,
    "cms_id": "product_6862_en_zh-hant",
    "container": null,
    "notified": 1,
    "tp_id": 103132,
    "word_count": 156
  },
  {
    "id": 147932,
    "website_id": 69873,
    "status": 4,
    "created_at": "2017-01-23T21:35:37.000Z",
    "updated_at": "2017-01-23T22:00:37.000Z",
    "language_id": 1,
    "title": "1.25mm CleanClicker® 750 Click-to-Clean Tool",
    "permlink": "https://sticklers.microcare.com/products/product/1-25mm-cleanclicker-750-click-to-clean-tool/",
    "tas_url": null,
    "tas_port": null,
    "list_type": null,
    "list_id": null,
    "last_operation": null,
    "pending_tas": 0,
    "error_description": null,
    "delivered": null,
    "note": "",
    "idkey": null,
    "cms_id": "product_6864_en_zh-hant",
    "container": null,
    "notified": 1,
    "tp_id": 103136,
    "word_count": 193
  },
  {
    "id": 147936,
    "website_id": 69873,
    "status": 4,
    "created_at": "2017-01-23T21:35:38.000Z",
    "updated_at": "2017-01-23T22:00:37.000Z",
    "language_id": 1,
    "title": "Cassette CleanClicker® Fiber Connector Cleaner",
    "permlink": "https://sticklers.microcare.com/products/product/cassette-cleanclicker-fiber-connector-cleaner/",
    "tas_url": null,
    "tas_port": null,
    "list_type": null,
    "list_id": null,
    "last_operation": null,
    "pending_tas": 0,
    "error_description": null,
    "delivered": null,
    "note": "",
    "idkey": null,
    "cms_id": "product_6865_en_zh-hant",
    "container": null,
    "notified": 1,
    "tp_id": 103140,
    "word_count": 135
  },
  {
    "id": 147940,
    "website_id": 69873,
    "status": 4,
    "created_at": "2017-01-23T21:35:39.000Z",
    "updated_at": "2017-01-23T22:00:37.000Z",
    "language_id": 1,
    "title": "EB CleanStixx® Optical Grade Cleaning Stick",
    "permlink": "https://sticklers.microcare.com/products/product/eb-cleanstixx-optical-grade-cleaning-stick/",
    "tas_url": null,
    "tas_port": null,
    "list_type": null,
    "list_id": null,
    "last_operation": null,
    "pending_tas": 0,
    "error_description": null,
    "delivered": null,
    "note": "",
    "idkey": null,
    "cms_id": "product_6866_en_zh-hant",
    "container": null,
    "notified": 1,
    "tp_id": 103144,
    "word_count": 143
  },
  {
    "id": 147944,
    "website_id": 69873,
    "status": 4,
    "created_at": "2017-01-23T21:54:20.000Z",
    "updated_at": "2017-01-23T22:00:37.000Z",
    "language_id": 1,
    "title": "Welcome to Sticklers® Fiber Optic Cleaners",
    "permlink": "https://sticklers.microcare.com/",
    "tas_url": null,
    "tas_port": null,
    "list_type": null,
    "list_id": null,
    "last_operation": null,
    "pending_tas": 0,
    "error_description": null,
    "delivered": null,
    "note": "",
    "idkey": null,
    "cms_id": "page_22_en_zh-hant",
    "container": null,
    "notified": 1,
    "tp_id": 103148,
    "word_count": 296
  },
  {
    "id": 147948,
    "website_id": 69873,
    "status": 4,
    "created_at": "2017-01-23T21:54:21.000Z",
    "updated_at": "2017-01-23T22:00:37.000Z",
    "language_id": 1,
    "title": "Fiber Optic Cleaning Products",
    "permlink": "https://sticklers.microcare.com/products/",
    "tas_url": null,
    "tas_port": null,
    "list_type": null,
    "list_id": null,
    "last_operation": null,
    "pending_tas": 0,
    "error_description": null,
    "delivered": null,
    "note": "",
    "idkey": null,
    "cms_id": "page_167_en_zh-hant",
    "container": null,
    "notified": 1,
    "tp_id": 103152,
    "word_count": 32
  }
]